ros2_easy/__init__.py
ros2_easy/simple_run.py
ros2_easy/classes/Cmd_Program.py
ros2_easy/classes/Config.py
ros2_easy/classes/Package.py
ros2_easy/classes/__init__.py
ros2_easy/classes/common_packages_and_programs.py
ros2_easy/classes/launch_configuration.py
ros2_easy/classes/logger.py
ros2_easy-0.4.dist-info/LICENSE
ros2_easy-0.4.dist-info/METADATA
ros2_easy-0.4.dist-info/WHEEL
ros2_easy-0.4.dist-info/top_level.txt
ros2_easy-0.4.dist-info/RECORD
