Metadata-Version: 2.1
Name: ros2-easy
Version: 0.4
Summary: A collection of tools to remove ROS2 worflow hurdles.
Home-page: https://github.com/rydb/ROS2_easy
Author: rydb
Author-email: rydb400@gmail.com
Classifier: Programming Language :: Python :: 3
Classifier: License :: OSI Approved :: GNU Lesser General Public License v2 or later (LGPLv2+)
Classifier: Operating System :: OS Independent
Requires-Python: >=3.8
License-File: LICENSE
